{"id":391,"name":"Monferno","genus":"Playful Pokémon","description":"To intimidate attackers, it stretches the fire on its tail to make itself appear bigger.","imageUrl":"https://pub-460ada4f152c4135a7ec0881a2cb1330.r2.dev/391.webp","types":["Fire","Fighting"],"abilities":[{"name":"Blaze","effect":"When this Pokémon has 1/3 or less of its HP remaining, its fire-type moves inflict 1.5× as much regular damage.","description":"Ups FIRE moves in a pinch."},{"name":"Iron Fist","effect":"Moves flagged as being punch-based have 1.2× their base power for this Pokémon.  sucker punch is not flagged as punch-based; its original, Japanese name only means \"surprise attack\".","description":"Boosts the power of punching moves."}],"stats":{"HP":64,"Attack":78,"Defense":52,"Special Attack":78,"Special Defense":52,"Speed":81},"locations":[],"color":"#f3d4b5"}