{"id":536,"name":"Palpitoad","genus":"Vibration Pokémon","description":"When they vibrate the bumps on their heads, they can make waves in water or earthquake-like vibrations on land.","imageUrl":"https://pub-460ada4f152c4135a7ec0881a2cb1330.r2.dev/536.webp","types":["Water","Ground"],"abilities":[{"name":"Swift Swim","effect":"This Pokémon's Speed is doubled during rain.  This bonus does not count as a stat modifier.","description":"Boosts the Pokémon's Speed in rain."},{"name":"Hydration","effect":"This Pokémon is cured of any major status ailment after each turn during rain.","description":"Heals status problems if it is raining."},{"name":"Water Absorb","effect":"Whenever a water-type move hits this Pokémon, it heals for 1/4 of its maximum HP, negating any other effect on it.  Water moves will ignore this Pokémon's substitute.","description":"Changes water into HP."}],"stats":{"HP":75,"Attack":65,"Defense":55,"Special Attack":65,"Special Defense":55,"Speed":69},"locations":["Icirrus City","Pinwheel Forest","Route 8","Moor of Icirrus"],"color":"#b7b7b8"}