{"id":633,"name":"Deino","genus":"Irate Pokémon","description":"It tends to bite everything, and it is not a picky eater. Approaching it carelessly is dangerous.","types":["Dark","Dragon"],"abilities":[{"name":"Hustle","effect":"This Pokémon's physical moves do 1.5× as much regular damage, but have 0.8× their usual accuracy.  Special moves are unaffected.  Moves that do set damage, such as seismic toss, have their accuracy affected, but not their damage.  Overworld: If the lead Pokémon has this ability, higher-levelled Pokémon have their encounter rate increased.","description":"Trades accuracy for power."}],"stats":{"HP":52,"Attack":65,"Defense":50,"Special Attack":45,"Special Defense":50,"Speed":38},"locations":["Victory Road"]}